jsonpatchext/__init__.py
jsonpatchext/comparators.py
jsonpatchext/jsonpatchext.py
jsonpatchext/mutators.py
jsonpatchext-1.39.dist-info/AUTHORS
jsonpatchext-1.39.dist-info/COPYING
jsonpatchext-1.39.dist-info/METADATA
jsonpatchext-1.39.dist-info/WHEEL
jsonpatchext-1.39.dist-info/top_level.txt
jsonpatchext-1.39.dist-info/RECORD
