Metadata-Version: 2.1
Name: jsonpatchext
Version: 1.39
Summary: Apply JSON-Patches (RFC 6902) with extensions 
Home-page: https://github.com/RangelReale/python-json-patch-ext
Author: Rangel Reale
Author-email: rangelspam@gmail.com
License: Modified BSD License
Project-URL: Website, https://github.com/RangelReale/python-json-patch-ext
Project-URL: Repository, https://github.com/RangelReale/python-json-patch-ext.git
Project-URL: Documentation, https://python-json-patch-ext.readthedocs.org/
Project-URL: PyPI, https://pypi.org/pypi/jsonpatchext
Platform: UNKNOWN
Classifier: Development Status :: 5 - Production/Stable
Classifier: Environment :: Console
Classifier: Intended Audience :: Developers
Classifier: License :: OSI Approved :: BSD License
Classifier: Operating System :: OS Independent
Classifier: Programming Language :: Python
Classifier: Programming Language :: Python :: 2
Classifier: Programming Language :: Python :: 2.7
Classifier: Programming Language :: Python :: 3
Classifier: Programming Language :: Python :: 3.5
Classifier: Programming Language :: Python :: 3.6
Classifier: Programming Language :: Python :: 3.7
Classifier: Programming Language :: Python :: 3.8
Classifier: Programming Language :: Python :: Implementation :: CPython
Classifier: Programming Language :: Python :: Implementation :: PyPy
Classifier: Topic :: Software Development :: Libraries
Classifier: Topic :: Utilities
Requires-Python: >=2.7, !=3.0.*, !=3.1.*, !=3.2.*, !=3.3.*, !=3.4.*
Requires-Dist: jsonpatch (>=1)
Requires-Dist: deepmerge (>=0.1)
Requires-Dist: future (>=0.18)
